shadow_useragent/__init__.py
shadow_useragent/core.py
shadow_useragent/test.py
shadow_useragent/data/infos.pk
shadow_useragent/data/useragents.pk
shadow_useragent-0.0.17.dist-info/LICENSE
shadow_useragent-0.0.17.dist-info/METADATA
shadow_useragent-0.0.17.dist-info/WHEEL
shadow_useragent-0.0.17.dist-info/top_level.txt
shadow_useragent-0.0.17.dist-info/RECORD
