Metadata-Version: 2.1
Name: shadow-useragent
Version: 0.0.17
Summary: Always get best user-agent
Home-page: https://github.com/Lobstrio/shadow-useragent
Author: Simon Rochwerg
Author-email: simon.rochwerg@lobstr.io
License: UNKNOWN
Platform: UNKNOWN
Classifier: Programming Language :: Python :: 3
Classifier: License :: OSI Approved :: MIT License
Classifier: Operating System :: OS Independent
